crescent/ext/kebab/__init__.py
crescent_ext_kebabify-0.1.2.dist-info/METADATA
crescent_ext_kebabify-0.1.2.dist-info/WHEEL
crescent_ext_kebabify-0.1.2.dist-info/RECORD
