Metadata-Version: 2.1
Name: crescent-ext-kebabify
Version: 0.1.2
Summary: Turn your command names into kebabs.
Home-page: https://github.com/Lunarmagpie/crescent-ext-kebabify
License: MPL-2.0
Author: Lunarmagpie
Author-email: Bambolambo0@gmail.com
Requires-Python: >=3.8,<3.12
Classifier: License :: OSI Approved
Classifier: Programming Language :: Python :: 3
Classifier: Programming Language :: Python :: 3.8
Classifier: Programming Language :: Python :: 3.9
Classifier: Programming Language :: Python :: 3.10
Classifier: Programming Language :: Python :: 3.11
Requires-Dist: hikari-crescent (>=0.5.0,<0.6.0)
Project-URL: Bug Tracker, https://github.com/Lunarmagpie/crescent-ext-kebabify/issues
Project-URL: Repository, https://github.com/Lunarmagpie/crescent-ext-kebabify
